{
  "orga_shit": [
    {
      "ZHdK": [ {
          "_old": [
          ]
        },
        {
          "_zhdk_resume_diploma": [
            null,
            null,
            null
          ]
        }
      ]
    },
    null,
    {
      "HSLU": [
        null,
        null,
        null,
        null,
        null
      ]
    },
    {
      "new_rechnungen": [
        null,
        {
          "konzepthausConslting": [
            null,
            null,
            {
              "baitStudios": [
                null
              ]
            },
            null,
            null,
            null,
            null,
            null,
            null,
            {
              "patxi_neu": [
                null,
                null,
                null,
                null,
                null,
                null,
                null,
                null,
                null,
                null,
                null,
                {
                  "old": [
                    null,
                    null
                  ]
                },
                null,
                null,
                null,
                null,
                null,
                null,
                null,
                null,
                null,
                null,
                null
              ]
            },
            null,
            null
          ]
        },
        null,
        null,
        null,
        {
          "patxi": [
            null,
            null,
            null,
            null,
            null,
            null,
            null,
            null,
            null,
            null,
            null,
            null,
            null,
            null,
            null,
            null,
            null,
            null,
            null,
            null
          ]
        },
        null,
        null,
        null,
        null,
        null,
        null,
        {
          "patxi_neu": [
            null,
            null,
            null,
            null,
            null,
            null,
            null,
            null,
            null,
            null,
            null,
            null,
            null,
            null,
            null,
            null,
            null,
            null,
            null,
            {
              "old": [
                null,
                null
              ]
            },
            null,
            null,
            null,
            null,
            null,
            null,
            null,
            null,
            null,
            null,
            null,
            null,
            null,
            null,
            null,
            null,
            null,
            null,
            null,
            null,
            null
          ]
        },
        null
      ]
    },
    {
      "teamviewer": [
        null
      ]
    },
    {
      "moving_with_araJOOO": [
        null,
        null,
        null,
        null
      ]
    },
    {
      "hslu_probezeit": [
        null,
        null
      ]
    },
    null
  ]
}